{
  "mo": {
    "ja": ["静けさ", "静かだ"],
    "en": ["silence", "quiet"],
    "ru": ["тишина", "тихо"]
  },
  "tere": {
    "ja": ["♪テレながら待つ"],
    "en": ["to wait shyly"],
    "ru": ["ждать застенчиво"]
  },
  "no": {
    "ja": ["-noを参照"],
    "en": ["see -no"],
    "ru": ["см. -no"]
  },
  "oruspe": {
    "ja": ["～の事柄", "～の噂", "～の事", "～の話"],
    "en": ["matter of ~", "rumor of ~", "story of ~"],
    "ru": ["дело о ~", "слух о ~", "история о ~"]
  },
  "tanpa": {
    "ja": ["本年", "今年"],
    "en": ["this year"],
    "ru": ["этот год"]
  },
  "hoko": {
    "ja": ["焚いた火"],
    "en": ["kindled fire"],
    "ru": ["разожженный огонь"]
  },
  "sinep": {
    "ja": ["一つ", "一人", "一頭"],
    "en": ["one (thing/person/animal)"],
    "ru": ["один (объект/человек/животное)"]
  },
  "y": {
    "ja": ["その間に挿入される"],
    "en": ["inserted in between"],
    "ru": ["вставляется между"]
  },
  "tup": {
    "ja": ["二つ", "二人", "二匹"],
    "en": ["two (things/people/animals)"],
    "ru": ["два (объекта/человека/животных)"]
  },
  "hetuku": {
    "ja": [
      "生まれる",
      "昇る",
      "生える",
      "出て来る",
      "芽を吹く",
      "輝き出る",
      "伸びる",
      "射し出づる",
      "差し始める",
      "出る",
      "生長する",
      "芽が出る",
      "顔を出す",
      "頭を出す"
    ],
    "en": ["to be born", "to rise", "to sprout", "to emerge"],
    "ru": ["родиться", "подниматься", "пускать ростки", "появляться"]
  },
  "utari": {
    "ja": ["utarの所属形"],
    "en": ["belonging to utar (people)"],
    "ru": ["принадлежность утару (люди)"]
  },
  "somo": {
    "ja": ["いや", "～しない", "～ない", "いいえ"],
    "en": ["no", "not ~", "to not do ~"],
    "ru": ["нет", "не ~", "не делать ~"]
  },
  "anki": {
    "ja": ["もう少しで～するところだった"],
    "en": ["almost about to ~"],
    "ru": ["почти собирался ~"]
  },
  "may": {
    "ja": ["気持ちがいい響き"],
    "en": ["pleasant sound"],
    "ru": ["приятный звук"]
  },
  "ra": {
    "ja": ["下下の方低い所"],
    "en": ["lower place", "beneath"],
    "ru": ["нижнее место", "внизу"]
  },
  "pak": {
    "ja": ["～ほど～ほどの"],
    "en": ["as much as ~", "to the extent of ~"],
    "ru": ["настолько как ~", "в мере ~"]
  },
  "urenkare": {
    "ja": ["全部揃える～を決める", "～解決する"],
    "en": ["to assemble everything", "to resolve ~"],
    "ru": ["собрать всё", "разрешить ~"]
  },
  "cup": {
    "ja": ["日"],
    "en": ["sun", "day"],
    "ru": ["солнце", "день"]
  },
  "iwanke": {
    "ja": ["達者である", "元気だ", "健康だ"],
    "en": ["to be healthy", "to be well"],
    "ru": ["быть здоровым", "чувствовать себя хорошо"]
  },
  "o": {
    "ja": ["～にある", "生える", "尻", "たくさんある", "ある", "付く"],
    "en": ["to exist at ~", "to grow", "to attach"],
    "ru": ["существовать в ~", "расти", "прикрепляться"]
  },
  "inunuka": {
    "ja": ["人を大事にする"],
    "en": ["to value people"],
    "ru": ["ценить людей"]
  },
  "ci": {
    "ja": ["それそこ自ら"],
    "en": ["itself", "oneself"],
    "ru": ["само", "себя"]
  },
  "irenka": {
    "ja": ["意図", "ルール"],
    "en": ["intention", "rule"],
    "ru": ["намерение", "правило"]
  },
  "orowano": {
    "ja": ["それから", "次に", "その後に"],
    "en": ["after that", "next"],
    "ru": ["после этого", "затем"]
  },
  "ho": {
    "ja": ["尻", "腰", "陰部", "陰門"],
    "en": ["buttocks", "waist", "genitals"],
    "ru": ["ягодицы", "талия", "гениталии"]
  },
  "ca": {
    "ja": ["口"],
    "en": ["mouth"],
    "ru": ["рот"]
  },
  "sinen": {
    "ja": ["一人"],
    "en": ["one person"],
    "ru": ["один человек"]
  },
  "ramma": {
    "ja": ["ずっと", "普段から", "相変わらず", "いつも"],
    "en": ["continuously", "always"],
    "ru": ["постоянно", "всегда"]
  },
  "ipere": {
    "ja": ["～にものを食べさせる", "たべものを与える", "食事をさせる"],
    "en": ["to feed ~", "to give food to ~"],
    "ru": ["кормить ~", "давать еду ~"]
  },
  "pu": {
    "ja": ["蔵"],
    "en": ["storehouse"],
    "ru": ["кладовая"]
  },
  "uwekari": {
    "ja": ["集う"],
    "en": ["to gather"],
    "ru": ["собираться"]
  }
}
